cauchycombt/__init__.py
cauchycombt/cct.py
cauchycombt-0.0.1.dist-info/METADATA
cauchycombt-0.0.1.dist-info/WHEEL
cauchycombt-0.0.1.dist-info/top_level.txt
cauchycombt-0.0.1.dist-info/RECORD
