Metadata-Version: 2.4
Name: cauchycombt
Version: 0.0.1
Summary: A package to perform Cauchy combination test.
Author-email: "Yao Lei (Leo)" <leiyao1997@outlook.com>
License: MIT
Project-URL: Homepage, https://github.com/YaoLei-Leo/cct
Project-URL: Issues, https://github.com/YaoLei-Leo/cct/issues
Requires-Python: >=3.0
Requires-Dist: scipy
Requires-Dist: numpy
